[
    {
        "id": "1",
        "title": "Funko Pop! Marvel: Deadpool",
        "description": "Funko Pop! Marvel: Deadpool",
        "price": 12.99
    },
    {
        "id": "2",
        "title": "Funko Pop! Marvel: Captain America",
        "description": "Funko Pop! Marvel: Captain America: Civil War Build A Scene - Captain America",
        "price": 12.22
    },
    {
        "id": "3",
        "title": "Funko Pop! Marvel: Iron Man",
        "description": "Funko Pop! Marvel: Captain America: Civil War Build A Scene - Iron Man",
        "price": 8.43
    }
]